core/__init__.py
core/model.py
core/patterns.py
core/scanner.py
errorforecaster-1.0.0.dist-info/licenses/LICENSE
report/__init__.py
tests/__init__.py
tests/test_forecaster.py
tests/test_sample.py
errorforecaster-1.0.0.dist-info/METADATA
errorforecaster-1.0.0.dist-info/WHEEL
errorforecaster-1.0.0.dist-info/entry_points.txt
errorforecaster-1.0.0.dist-info/top_level.txt
errorforecaster-1.0.0.dist-info/RECORD
